s3sim/__init__.py
s3sim/s3_operations.py
s3sim/tests/__init__.py
s3sim/tests/test_s3_operations.py
s3sim-0.1.0.dist-info/METADATA
s3sim-0.1.0.dist-info/WHEEL
s3sim-0.1.0.dist-info/entry_points.txt
s3sim-0.1.0.dist-info/top_level.txt
s3sim-0.1.0.dist-info/RECORD
